Metadata-Version: 2.4
Name: eval-ai-library
Version: 0.4.40
Summary: Comprehensive AI Model Evaluation Framework with support for multiple LLM providers
Author-email: Aleksandr Meshkov <alekslynx90@gmail.com>
License: Apache License 2.0
Project-URL: Homepage, https://github.com/meshkovQA/Eval-ai-library
Project-URL: Documentation, https://github.com/meshkovQA/Eval-ai-library#readme
Project-URL: Repository, https://github.com/meshkovQA/Eval-ai-library
Project-URL: Bug Tracker, https://github.com/meshkovQA/Eval-ai-library/issues
Keywords: ai,evaluation,llm,rag,metrics,testing,quality-assurance
Classifier: Development Status :: 4 - Beta
Classifier: Intended Audience :: Developers
Classifier: Intended Audience :: Science/Research
Classifier: License :: OSI Approved :: Apache Software License
Classifier: Programming Language :: Python :: 3
Classifier: Programming Language :: Python :: 3.9
Classifier: Programming Language :: Python :: 3.10
Classifier: Programming Language :: Python :: 3.11
Classifier: Programming Language :: Python :: 3.12
Classifier: Topic :: Scientific/Engineering :: Artificial Intelligence
Classifier: Topic :: Software Development :: Libraries :: Python Modules
Requires-Python: >=3.9
License-File: LICENSE
Requires-Dist: openai>=1.0.0
Requires-Dist: anthropic>=0.18.0
Requires-Dist: google-genai>=0.2.0
Requires-Dist: pydantic>=2.0.0
Requires-Dist: numpy>=1.24.0
Requires-Dist: langchain>=0.1.0
Requires-Dist: langchain-community>=0.0.10
Requires-Dist: langchain-core>=0.1.0
Requires-Dist: langchain-text-splitters>=0.2.0
Requires-Dist: pypdf>=3.0.0
Requires-Dist: python-docx>=0.8.11
Requires-Dist: openpyxl>=3.1.0
Requires-Dist: pillow>=10.0.0
Requires-Dist: pytesseract>=0.3.10
Requires-Dist: python-pptx>=0.6.21
Requires-Dist: PyMuPDF>=1.23.0
Requires-Dist: mammoth>=1.6.0
Requires-Dist: PyYAML>=6.0.0
Requires-Dist: html2text>=2020.1.16
Requires-Dist: markdown>=3.4.0
Requires-Dist: pandas>=2.0.0
Requires-Dist: striprtf>=0.0.26
Requires-Dist: transformers>=4.30.0
Requires-Dist: torch>=2.0.0
Requires-Dist: presidio-analyzer>=2.2.0
Requires-Dist: spacy<3.8.0,>=3.0.0
Requires-Dist: flask>=3.0.0
Requires-Dist: aiohttp>=3.8.0
Provides-Extra: lite
Requires-Dist: pydantic>=2.0.0; extra == "lite"
Requires-Dist: aiohttp>=3.8.0; extra == "lite"
Provides-Extra: dev
Requires-Dist: pytest>=7.0.0; extra == "dev"
Requires-Dist: pytest-asyncio>=0.21.0; extra == "dev"
Requires-Dist: black>=23.0.0; extra == "dev"
Requires-Dist: flake8>=6.0.0; extra == "dev"
Requires-Dist: mypy>=1.0.0; extra == "dev"
Requires-Dist: isort>=5.12.0; extra == "dev"
Provides-Extra: docs
Requires-Dist: sphinx>=6.0.0; extra == "docs"
Requires-Dist: sphinx-rtd-theme>=1.2.0; extra == "docs"
Dynamic: license-file
